LICENSE
MANIFEST.in
README.md
package.json
setup.py
dl_test/4574978-179-wps-hmr.js
dl_test/4574978-179-wps-hmr.js.map
dl_test/BaseLayer.py
dl_test/Circle.py
dl_test/CircleMarker.py
dl_test/Colorbar.py
dl_test/DivMarker.py
dl_test/EasyButton.py
dl_test/EditControl.py
dl_test/FeatureGroup.py
dl_test/FullscreenControl.py
dl_test/GeoJSON.py
dl_test/GeoTIFFOverlay.py
dl_test/GestureHandling.py
dl_test/HeatmapLayer.py
dl_test/ImageOverlay.py
dl_test/LayerGroup.py
dl_test/LayersControl.py
dl_test/LocateControl.py
dl_test/Map.py
dl_test/Marker.py
dl_test/MarkerClusterGroup.py
dl_test/MeasureControl.py
dl_test/Minichart.py
dl_test/Overlay.py
dl_test/Pane.py
dl_test/Polygon.py
dl_test/Polyline.py
dl_test/PolylineDecorator.py
dl_test/Popup.py
dl_test/Rectangle.py
dl_test/SVGOverlay.py
dl_test/ScaleControl.py
dl_test/TileLayer.py
dl_test/Tooltip.py
dl_test/VideoOverlay.py
dl_test/WMSTileLayer.py
dl_test/__init__.py
dl_test/_imports_.py
dl_test/async-editControl.js
dl_test/async-editControl.js.map
dl_test/async-geoTiffOverlay.js
dl_test/async-geoTiffOverlay.js.map
dl_test/async-locateControl.js
dl_test/async-locateControl.js.map
dl_test/async-markerClusterGroup.js
dl_test/async-markerClusterGroup.js.map
dl_test/async-measureControl.js
dl_test/async-measureControl.js.map
dl_test/async-minichart.js
dl_test/async-minichart.js.map
dl_test/async-null.js
dl_test/async-null.js.map
dl_test/dash_leaflet.min.js
dl_test/dash_leaflet.min.js.map
dl_test/dl_test.min.js
dl_test/dl_test.min.js.map
dl_test/express.py
dl_test/leaflet@1.8.0.css
dl_test/leaflet@1.8.0.js
dl_test/main-4574978-wps-hmr.json
dl_test/metadata.json
dl_test/package-info.json
dl_test/react-leaflet@2.8.0.js
dl_test.egg-info/PKG-INFO
dl_test.egg-info/SOURCES.txt
dl_test.egg-info/dependency_links.txt
dl_test.egg-info/requires.txt
dl_test.egg-info/top_level.txt