Metadata-Version: 2.1
Name: dl-test
Version: 0.1.7
Summary: Dl test
Home-page: UNKNOWN
Author: fj-blanco <fjavib@gmail.com>
License: MIT
Platform: UNKNOWN
